EnergyDiagramPlotter/EnergyLeveler.py
EnergyDiagramPlotter/__init__.py
ed_maker-0.0.1.dist-info/METADATA
ed_maker-0.0.1.dist-info/WHEEL
ed_maker-0.0.1.dist-info/top_level.txt
ed_maker-0.0.1.dist-info/RECORD
